alu.v
module alu(
  input [31:0] op1,
  input [31:0] op2,
  input [3:0] alu_op,
  output zero,
  output [31:0] result
  );
 
  parameter[3:0] ALUOP_AND = 4'b0000;
  parameter[3:0] ALUOP_OR  = 4'b0001;
  parameter[3:0] ALUOP_ADD = 4'b0010;
  parameter[3:0] ALUOP_SUB = 4'b0110;
  parameter[3:0] ALUOP_SLT = 4'b0100;
  parameter[3:0] ALUOP_LSR = 4'b1000;
  parameter[3:0] ALUOP_LSL = 4'b1001;
  parameter[3:0] ALUOP_ASR = 4'b1010;
  parameter[3:0] ALUOP_XOR = 4'b0101;
  
  reg [31:0] res;

  always @(*) begin
    case (alu_op)
            ALUOP_AND: res = op1 & op2;
            ALUOP_OR: res = op1 | op2;
            ALUOP_ADD: res = op1 + op2;
            ALUOP_SUB: res = op1 - op2;
      		  ALUOP_SLT: res = ($signed(op1) < $signed(op2)) ? 32'd1 : 32'd0;
      	    ALUOP_LSR: res = op1 >> op2[4:0];
            ALUOP_LSL: res = op1 << op2[4:0];
      		  ALUOP_ASR: res = ($signed(op1)) >>> op2[4:0];
      		  ALUOP_XOR: res = op1 ^ op2;
            default: res = 32'd0;
        endcase
    end

	assign result = res;

  assign zero = (res == 32'd0) ? 1'b1 : 1'b0;

endmodule

calc_enc.v
module calc_enc(
  input btnl,
  input btnc,
  input btnr,
  output wire [3:0] alu_op
  );
  
  wire not_btnc,not_btnl,not_btnr;
  wire and1_out,and2_out,and3_out,and4_out,
  and5_out,and6_out,and7_out,
  and8_out,and9_out,and10_out,and11_out;

  //alu_op[0]
  not(not_btnc,btnc);

  and(and1_out,not_btnc,btnr);
  and(and2_out,btnl,btnr);

  or(alu_op[0],and1_out,and2_out);

  //alu_op[1]
  not(not_btnl,btnl);
  not(not_btnr,btnr);

  and(and3_out,not_btnl,btnc);
  and(and4_out,btnc,not_btnr);
  	
  or(alu_op[1],and3_out,and4_out);
  
  //alu_op[2]
  and(and5_out,btnl,not_btnc);
  and(and6_out,btnc,btnr);
  and(and7_out,and5_out,not_btnr);
  
  or(alu_op[2],and6_out,and7_out);

  //alu_op[3]
  and(and8_out,btnl,not_btnc);
  and(and9_out,btnl,btnc);
  and(and10_out,and8_out,btnr);
  and(and11_out,and9_out,not_btnr);

  or(alu_op[3],and10_out,and11_out); 
endmodule

calc.v
module calc(
  input clk,
  input btnc,
  input btnl,
  input btnu,
  input btnr,
  input btnd,
  input [15:0] sw,
  output [15:0] led
  );

  reg [15:0] accumulator;
  wire [31:0] alu_result;
  wire [31:0] op1 = {{16{accumulator[15]}}, accumulator};
  wire [31:0] op2 = {{16{sw[15]}}, sw};
  wire [3:0] alu_op;
  
  calc_enc CALC_ENC(
    .btnl(btnl),
    .btnc(btnc),
    .btnr(btnr),
    .alu_op(alu_op)
  );
  
  alu ALU(
    .op1(op1),
    .op2(op2),
    .alu_op(alu_op),
    .zero(),
    .result(alu_result)
    );
  
  always @(posedge clk) begin  
    if (btnu == 1) begin
          accumulator <= 16'b0; // Reset accumulator when `btnu` is pressed
    end else if (btnd == 1) begin
          accumulator <= alu_result[15:0]; // Update accumulator when `btnd` is pressed
    end
  end
  
  assign led = accumulator;
  
endmodule

calc_tb.v
module calc_tb();
  
  // Declare registers and wires for the testbench
  reg clk;
  reg btnc, btnl, btnu, btnr, btnd;
  reg [15:0] sw;
  wire [15:0] led;
  
  // Instantiate the calc DUT
  calc CALC(
    .clk(clk),
    .btnc(btnc),
    .btnl(btnl),
    .btnu(btnu),
    .btnr(btnr),
    .btnd(btnd),
    .sw(sw),
    .led(led)
  );
  
  // Clock generation
  initial begin
    clk = 0;
    forever #5 clk = ~clk;  // Toggle clock every 5 time units (10 ns period)
  end
  
    // Dump waveforms for simulation
  initial begin
    $dumpfile("dump.vcd"); // Specify the dump file name
    $dumpvars;             // Dump all variables to the file
  end

  
  // Test sequence
  initial begin
    // Initialize inputs
    btnc = 0;
    btnl = 0;
    btnu = 0;
    btnr = 0;
    btnd = 0;
    sw = 16'h0000;
    
    // Reset the accumulator
    #10 btnu = 1;  // Press reset button
    #10 btnu = 0;  // Release reset button
    #10; // Wait a bit
    
    // Apply Test Cases
    // Test case 1: ADD operation (0,1,0) - 0x0 + 0x354a -> Expected 0x354a
    btnl = 0;
    btnc = 1;
    btnr = 0;
    sw = 16'h354a;  // Input switches
    btnd = 1;  // Apply ALU operation
    #10 btnd = 0; // Release the button
    #20; // Wait to apply next operation
    $display("ADD: Expected: 0x354a, Got: %h", led);
    
    // Test case 2: SUB operation (0,1,1) - 0x354a - 0x1234 -> Expected 0x2316
    btnl = 0;
    btnc = 1;
    btnr = 1;
    sw = 16'h1234;  // Input switches
    btnd = 1;  // Apply ALU operation
    #10 btnd = 0; // Release the button
    #10; // Wait to apply next operation
    $display("SUB: Expected: 0x2316, Got: %h", led);

    // Test case 3: OR operation (0,0,1) - 0x2316 | 0x1001 -> Expected 0x3317
    btnl = 0; 
    btnc = 0; 
    btnr = 1;
    sw = 16'h1001;  // Input switches
    btnd = 1;  // Apply ALU operation
    #10 btnd = 0;
    #10;
    $display("OR: Expected: 0x3317, Got: %h", led);

    // Test case 4: AND operation (0,0,0) - 0x3317 & 0xf0f0 -> Expected 0x3010
    btnl = 0; 
    btnc = 0; 
    btnr = 0;
    sw = 16'hf0f0;  // Input switches
    btnd = 1;  // Apply ALU operation
    #10 btnd = 0;
    #10;
    $display("AND: Expected: 0x3010, Got: %h", led);

    // Test case 5: XOR operation (1,1,1) - 0x3010 ^ 0x1fa2 -> Expected 0x2fb2
    btnl = 1; 
    btnc = 1; 
    btnr = 1;
    sw = 16'h1fa2;  // Input switches
    btnd = 1;  // Apply ALU operation
    #10 btnd = 0;
    #10;
    $display("XOR: Expected: 0x2fb2, Got: %h", led);

    // Test case 6: ADD operation (0,1,0) - 0x2fb2 + 0x6aa2 -> Expected 0x9a54
    btnl = 0; 
    btnc = 1; 
    btnr = 0;
    sw = 16'h6aa2;  // Input switches
    btnd = 1;  // Apply ALU operation
    #10 btnd = 0;
    #10;
    $display("ADD: Expected: 0x9a54, Got: %h", led);

    // Test case 7: Logical Shift Left (1,0,1) - 0x9a54 << 1 -> Expected 0xa540
    btnl = 1; 
    btnc = 0; 
    btnr = 1;
    sw = 16'h0004;  // Input switches (Shift value)
    btnd = 1;  // Apply ALU operation
    #10 btnd = 0;
    #10;
    $display("Logical Shift Left: Expected: 0xa540, Got: %h", led);

    // Test case 8: Shift Right Arithmetic (1,1,0) - 0xa540 >> 1 -> Expected 0xd2a0
    btnl = 1; 
    btnc = 1; 
    btnr = 0;
    sw = 16'h0001;  // Input switches (Shift value)
    btnd = 1;  // Apply ALU operation
    #10 btnd = 0;
    #10;
    $display("Shift Right Arithmetic: Expected: 0xd2a0, Got: %h", led);

    // Test case 9: Less Than (1,0,0) - (0xd2a0 < 0x46ff) -> Expected 0x0001
    btnl = 1; 
    btnc = 0; 
    btnr = 0;
    sw = 16'h46ff;  // Input switches
    btnd = 1;  // Apply ALU operation
    #10 btnd = 0;
    #10;
    $display("Less Than: Expected: 0x0001, Got: %h", led);		
    
    // Finish simulation after a while
    #100;
    $finish;
  end
endmodule

dump.vcd
$date
	Thu Dec 05 10:11:36 2024
$end
$version
	Icarus Verilog
$end
$timescale
	1s
$end
$scope module calc_tb $end
$var wire 16 ! led [15:0] $end
$var reg 1 " btnc $end
$var reg 1 # btnd $end
$var reg 1 $ btnl $end
$var reg 1 % btnr $end
$var reg 1 & btnu $end
$var reg 1 ' clk $end
$var reg 16 ( sw [15:0] $end
$scope module CALC $end
$var wire 1 " btnc $end
$var wire 1 # btnd $end
$var wire 1 $ btnl $end
$var wire 1 % btnr $end
$var wire 1 & btnu $end
$var wire 1 ' clk $end
$var wire 16 ) led [15:0] $end
$var wire 16 * sw [15:0] $end
$var wire 32 + op2 [31:0] $end
$var wire 32 , op1 [31:0] $end
$var wire 32 - alu_result [31:0] $end
$var wire 4 . alu_op [3:0] $end
$var reg 16 / accumulator [15:0] $end
$scope module ALU $end
$var wire 32 0 op1 [31:0] $end
$var wire 32 1 op2 [31:0] $end
$var wire 32 2 result [31:0] $end
$var wire 1 3 zero $end
$var wire 4 4 alu_op [3:0] $end
$var parameter 4 5 ALUOP_ADD $end
$var parameter 4 6 ALUOP_AND $end
$var parameter 4 7 ALUOP_ASR $end
$var parameter 4 8 ALUOP_LSL $end
$var parameter 4 9 ALUOP_LSR $end
$var parameter 4 : ALUOP_OR $end
$var parameter 4 ; ALUOP_SLT $end
$var parameter 4 < ALUOP_SUB $end
$var parameter 4 = ALUOP_XOR $end
$var reg 32 > res [31:0] $end
$upscope $end
$scope module CALC_ENC $end
$var wire 1 ? and10_out $end
$var wire 1 @ and11_out $end
$var wire 1 A and1_out $end
$var wire 1 B and2_out $end
$var wire 1 C and3_out $end
$var wire 1 D and4_out $end
$var wire 1 E and5_out $end
$var wire 1 F and6_out $end
$var wire 1 G and7_out $end
$var wire 1 H and8_out $end
$var wire 1 I and9_out $end
$var wire 1 " btnc $end
$var wire 1 $ btnl $end
$var wire 1 % btnr $end
$var wire 1 J not_btnc $end
$var wire 1 K not_btnl $end
$var wire 1 L not_btnr $end
$var wire 4 M alu_op [3:0] $end
$upscope $end
$upscope $end
$upscope $end
$enddefinitions $end
$comment Show the parameter values. $end
$dumpall
b101 =
b110 <
b100 ;
b1 :
b1000 9
b1001 8
b1010 7
b0 6
b10 5
$end
#0
$dumpvars
b0 M
1L
1K
1J
0I
0H
0G
0F
0E
0D
0C
0B
0A
0@
0?
b0 >
b0 4
13
b0 2
b0 1
bx 0
bx /
b0 .
b0 -
bx ,
b0 +
b0 *
bx )
b0 (
0'
0&
0%
0$
0#
0"
bx !
$end
#5
1'
#10
0'
1&
#15
b0 ,
b0 0
b0 !
b0 )
b0 /
1'
#20
0'
0&
#25
1'
#30
03
b11010101001010 -
b11010101001010 2
b11010101001010 >
b10 .
b10 4
b10 M
0J
1C
1D
0'
1#
b11010101001010 +
b11010101001010 1
b11010101001010 (
b11010101001010 *
1"
#35
b110101010010100 -
b110101010010100 2
b110101010010100 >
b11010101001010 ,
b11010101001010 0
b11010101001010 !
b11010101001010 )
b11010101001010 /
1'
#40
0'
0#
#45
1'
#50
0'
#55
1'
#60
0D
b110 .
b110 4
b110 M
b10001100010110 -
b10001100010110 2
b10001100010110 >
0L
1F
0'
1#
b1001000110100 +
b1001000110100 1
b1001000110100 (
b1001000110100 *
1%
#65
b1000011100010 -
b1000011100010 2
b1000011100010 >
b10001100010110 ,
b10001100010110 0
b10001100010110 !
b10001100010110 )
b10001100010110 /
1'
#70
0'
0#
#75
1'
#80
03
1A
b1 .
b1 4
b1 M
b11001100010111 -
b11001100010111 2
b11001100010111 >
1J
0C
0F
0'
1#
b1000000000001 +
b1000000000001 1
b1000000000001 (
b1000000000001 *
0"
#85
b11001100010111 ,
b11001100010111 0
b11001100010111 !
b11001100010111 )
b11001100010111 /
1'
#90
0'
0#
#95
1'
#100
b0 .
b0 4
b0 M
b11000000010000 -
b11000000010000 2
b11000000010000 >
0A
1L
0'
1#
b11111111111111111111000011110000 +
b11111111111111111111000011110000 1
b1111000011110000 (
b1111000011110000 *
0%
#105
b11000000010000 ,
b11000000010000 0
b11000000010000 !
b11000000010000 )
b11000000010000 /
1'
#110
0'
0#
#115
1'
#120
03
b101 .
b101 4
b101 M
b10111110110010 -
b10111110110010 2
b10111110110010 >
0L
0?
0J
0D
1F
1B
0K
0E
0H
1I
0'
1#
b1111110100010 +
b1111110100010 1
b1111110100010 (
b1111110100010 *
1%
1"
1$
#125
b11000000010000 -
b11000000010000 2
b11000000010000 >
b10111110110010 ,
b10111110110010 0
b10111110110010 !
b10111110110010 )
b10111110110010 /
1'
#130
0'
0#
#135
1'
#140
1D
b10 .
b10 4
b10 M
1C
b1001101001010100 -
b1001101001010100 2
b1001101001010100 >
1L
0F
0B
1K
0I
0'
1#
b110101010100010 +
b110101010100010 1
b110101010100010 (
b110101010100010 *
0%
0$
#145
b10011110110 -
b10011110110 2
b10011110110 >
b11111111111111111001101001010100 ,
b11111111111111111001101001010100 0
b1001101001010100 !
b1001101001010100 )
b1001101001010100 /
1'
#150
0'
0#
#155
1'
#160
1?
1E
1H
b1001 .
b1001 4
b1001 M
b11111111111110011010010101000000 -
b11111111111110011010010101000000 2
b11111111111110011010010101000000 >
1A
0L
1J
0C
0D
1B
0K
0'
1#
b100 +
b100 1
b100 (
b100 *
1%
0"
1$
#165
b11111111111110100101010000000000 -
b11111111111110100101010000000000 2
b11111111111110100101010000000000 >
b11111111111111111010010101000000 ,
b11111111111111111010010101000000 0
b1010010101000000 !
b1010010101000000 )
b1010010101000000 /
1'
#170
0'
0#
#175
1'
#180
b1010 .
b1010 4
b1010 M
1D
0E
0H
1@
b11111111111111111101001010100000 -
b11111111111111111101001010100000 2
b11111111111111111101001010100000 >
0A
0B
1L
0?
0J
1I
0'
1#
b1 +
b1 1
b1 (
b1 *
0%
1"
#185
b11111111111111111110100101010000 -
b11111111111111111110100101010000 2
b11111111111111111110100101010000 >
b11111111111111111101001010100000 ,
b11111111111111111101001010100000 0
b1101001010100000 !
b1101001010100000 )
b1101001010100000 /
1'
#190
0'
0#
#195
1'
#200
1G
1E
1H
b100 .
b100 4
b100 M
0@
b1 -
b1 2
b1 >
1J
0D
0I
0'
1#
b100011011111111 +
b100011011111111 1
b100011011111111 (
b100011011111111 *
0"
#205
b1 ,
b1 0
b1 !
b1 )
b1 /
1'
#210
0'
0#
